setup.cfg
setup.py
csp_report/__init__.py
csp_report/admin.py
csp_report/models.py
csp_report/urls.py
csp_report/utils.py
csp_report/views.py
csp_report/management/__init__.py
csp_report/management/commands/__init__.py
csp_report/management/commands/csp_cleanup.py
csp_report/migrations/0001_initial.py
csp_report/migrations/0002_cleanedcspreport.py
csp_report/migrations/0003_cspreportfilter.py
csp_report/migrations/__init__.py
django_cspreport.egg-info/PKG-INFO
django_cspreport.egg-info/SOURCES.txt
django_cspreport.egg-info/dependency_links.txt
django_cspreport.egg-info/top_level.txt