Metadata-Version: 1.0
Name: django-cspreport
Version: 0.1.11
Summary: Django app for handling reports from web browsers of violations of content security policy.
Home-page: https://github.com/atuchak/django-cspreport
Author: Anton Tuchak
Author-email: anton.tuchak@gmail.com
License: UNKNOWN
Keywords: Content-Security-Policy,csp,Django
Platform: UNKNOWN
